datanomy/__init__.py
datanomy/cli.py
datanomy/reader/parquet.py
datanomy/tui/common.py
datanomy/tui/parquet.py
datanomy/tui/tui.py
datanomy/utils.py
datanomy-0.2.1.dist-info/WHEEL
datanomy-0.2.1.dist-info/entry_points.txt
datanomy-0.2.1.dist-info/METADATA
datanomy-0.2.1.dist-info/RECORD
