Metadata-Version: 2.3
Name: datanomy
Version: 0.2.1
Summary: Explore the anatomy of your columnar data files (Parquet, Arrow, and more)
Author: Raúl Cumplido
Author-email: Raúl Cumplido <raulcumplido@gmail.com>
Requires-Dist: textual>=0.90.0
Requires-Dist: pyarrow>=22.0.0
Requires-Dist: rich>=13.0.0
Requires-Dist: click>=8.1.0
Requires-Dist: pytest>=8.0.0 ; extra == 'dev'
Requires-Dist: pytest-cov>=4.0.0 ; extra == 'dev'
Requires-Dist: ruff>=0.8.0 ; extra == 'dev'
Requires-Dist: mypy>=1.0.0 ; extra == 'dev'
Requires-Dist: pytest-asyncio>=1.2.0 ; extra == 'dev'
Requires-Python: >=3.10
Project-URL: Homepage, https://github.com/raulcd/datanomy
Project-URL: Issues, https://github.com/raulcd/datanomy/issues
Project-URL: Repository, https://github.com/raulcd/datanomy
Provides-Extra: dev
